graphbit-0.5.1.dist-info/METADATA
graphbit-0.5.1.dist-info/WHEEL
graphbit-0.5.1.dist-info/licenses/LICENSE.md
graphbit/__init__.py
graphbit/graphbit.cpython-312-aarch64-linux-gnu.so
graphbit-0.5.1.dist-info/RECORD
